<?xml version="1.0" encoding="utf-8"?>
<AppVariables version="2.0">
  <Datasets>
    <Dataset id="gds_headerInfo">
      <ColumnInfo>
        <Column id="MENU_ID" type="STRING" size="256"/>
        <Column id="MENU_NM" type="STRING" size="256"/>
        <Column id="MENU_LEVEL" type="STRING" size="256"/>
        <Column id="MENU_PATH" type="STRING" size="256"/>
      </ColumnInfo>
      <Rows>
        <Row>
          <Col id="MENU_ID">00</Col>
          <Col id="MENU_NM">공통</Col>
          <Col id="MENU_LEVEL">0</Col>
          <Col id="MENU_PATH"/>
        </Row>
        <Row>
          <Col id="MENU_ID">0000</Col>
          <Col id="MENU_NM">공통</Col>
          <Col id="MENU_LEVEL">1</Col>
          <Col id="MENU_PATH"/>
        </Row>
        <Row>
          <Col id="MENU_ID">000000</Col>
          <Col id="MENU_NM">- 공통코드</Col>
          <Col id="MENU_LEVEL">2</Col>
          <Col id="MENU_PATH">FrameBase::Form_Common.xfdl</Col>
        </Row>
        <Row>
          <Col id="MENU_ID">01</Col>
          <Col id="MENU_NM">회원관리</Col>
          <Col id="MENU_LEVEL">0</Col>
          <Col id="MENU_PATH"/>
        </Row>
        <Row>
          <Col id="MENU_ID">0101</Col>
          <Col id="MENU_NM">회원관리</Col>
          <Col id="MENU_LEVEL">1</Col>
          <Col id="MENU_PATH"/>
        </Row>
        <Row>
          <Col id="MENU_ID">010000</Col>
          <Col id="MENU_NM">- 회원관리</Col>
          <Col id="MENU_LEVEL">2</Col>
          <Col id="MENU_PATH">dept::Form_User.xfdl</Col>
        </Row>
        <Row>
          <Col id="MENU_ID">02</Col>
          <Col id="MENU_NM">상품관리</Col>
          <Col id="MENU_LEVEL">0</Col>
        </Row>
        <Row>
          <Col id="MENU_ID">0200</Col>
          <Col id="MENU_NM">상품관리</Col>
          <Col id="MENU_LEVEL">1</Col>
        </Row>
        <Row>
          <Col id="MENU_ID">020000</Col>
          <Col id="MENU_NM">- 상품목록조회</Col>
          <Col id="MENU_LEVEL">2</Col>
          <Col id="MENU_PATH">product::Form_ProductT.xfdl</Col>
        </Row>
        <Row>
          <Col id="MENU_ID">03</Col>
          <Col id="MENU_NM">주문관리</Col>
          <Col id="MENU_LEVEL">0</Col>
        </Row>
        <Row>
          <Col id="MENU_ID">0300</Col>
          <Col id="MENU_NM">주문관리</Col>
          <Col id="MENU_LEVEL">1</Col>
        </Row>
        <Row>
          <Col id="MENU_ID">030000</Col>
          <Col id="MENU_NM">- 주문목록조회</Col>
          <Col id="MENU_LEVEL">2</Col>
          <Col id="MENU_PATH">Order::Form_OrderList.xfdl</Col>
        </Row>
        <Row>
          <Col id="MENU_ID">030001</Col>
          <Col id="MENU_NM">- 배송관리</Col>
          <Col id="MENU_LEVEL">2</Col>
          <Col id="MENU_PATH">Order::Form_Shipping.xfdl</Col>
        </Row>
        <Row>
          <Col id="MENU_ID">030002</Col>
          <Col id="MENU_NM">- 환불관리</Col>
          <Col id="MENU_LEVEL">2</Col>
          <Col id="MENU_PATH">Order::Form_Refund.xfdl</Col>
        </Row>
        <Row>
          <Col id="MENU_ID">04</Col>
          <Col id="MENU_NM">통계</Col>
          <Col id="MENU_LEVEL">0</Col>
        </Row>
        <Row>
          <Col id="MENU_ID">0400</Col>
          <Col id="MENU_NM">통계</Col>
          <Col id="MENU_LEVEL">1</Col>
        </Row>
        <Row>
          <Col id="MENU_ID">040001</Col>
          <Col id="MENU_NM">- 상품별통계</Col>
          <Col id="MENU_LEVEL">2</Col>
          <Col id="MENU_PATH">Calculator::Form_ProductCal.xfdl</Col>
        </Row>
        <Row>
          <Col id="MENU_ID">040002</Col>
          <Col id="MENU_NM">- 회원별통계</Col>
          <Col id="MENU_LEVEL">2</Col>
          <Col id="MENU_PATH">Calculator::Form_UserCal.xfdl</Col>
        </Row>
      </Rows>
    </Dataset>
  </Datasets>
  <Variables/>
  <DataObjects/>
</AppVariables>
